proteinTools/PT.py
proteinTools/__init__.py
proteinTools-2.2.4.dist-info/LICENSE
proteinTools-2.2.4.dist-info/METADATA
proteinTools-2.2.4.dist-info/WHEEL
proteinTools-2.2.4.dist-info/top_level.txt
proteinTools-2.2.4.dist-info/RECORD
