Metadata-Version: 2.1
Name: proteinTools
Version: 2.2.4
Summary: Lightweight, object-oriented backend bioinformatics package which simplifies interacting with proteins.
Author: Christian de Frondeville
License-File: LICENSE
Requires-Dist: pandas
Requires-Dist: urllib3
Requires-Dist: mygene
Requires-Dist: pubchempy
Requires-Dist: stringdb
Requires-Dist: chembl-webresource-client
